wallet_pass/__init__.py
wallet_pass/cli.py
wallet_pass/config.py
wallet_pass/exceptions.py
wallet_pass/logging.py
wallet_pass/providers/__init__.py
wallet_pass/providers/apple_pass.py
wallet_pass/providers/base.py
wallet_pass/providers/google_pass.py
wallet_pass/providers/manager.py
wallet_pass/providers/samsung_pass.py
wallet_pass/schema/__init__.py
wallet_pass/schema/core.py
wallet_pass/storage.py
wallet_pass/utils.py
py_wallet_pass-0.1.3.dist-info/LICENSE
py_wallet_pass-0.1.3.dist-info/METADATA
py_wallet_pass-0.1.3.dist-info/WHEEL
py_wallet_pass-0.1.3.dist-info/entry_points.txt
py_wallet_pass-0.1.3.dist-info/RECORD
