Metadata-Version: 2.1
Name: py-wallet-pass
Version: 0.1.3
Summary: SDK for easily creating/managing Apple and Google wallet passes.
License: CC BY-NC 4.0
Author: DuneRaccoon
Author-email: benjamincsherro@hotmail.com
Requires-Python: >=3.10,<4.0
Classifier: License :: Other/Proprietary License
Classifier: Programming Language :: Python :: 3
Classifier: Programming Language :: Python :: 3.10
Classifier: Programming Language :: Python :: 3.11
Classifier: Programming Language :: Python :: 3.12
Requires-Dist: google-api-python-client (>=2.165.0,<3.0.0)
Requires-Dist: google-auth (>=2.38.0,<3.0.0)
Requires-Dist: loguru (>=0.7.2,<0.8.0)
Requires-Dist: pydantic (>=2.10.6,<3.0.0)
Requires-Dist: pyopenssl (>=25.0.0,<26.0.0)
Requires-Dist: rich (>=13.7.1,<14.0.0)
Requires-Dist: typer (>=0.9.0,<0.10.0)
